traffic_controller.v
module traffic_light_controller(
     clk,rst,light_M1,light_s,light_MT,light_M2);

     input clk,rst;
     output reg [2:0]light_M1 ;
    output reg [2:0]light_s ;
    output reg [2:0]light_MT ;
    output reg [2:0]light_M2 ;

    parameter S1=0, S2=1, S3=2, S4=3, S5=4, S6=5;
    reg [3:0]count ;
    reg [2:0] ps ;
    parameter sec7=7, sec5=5, sec2=2, sec3=3 ;


    always@(posedge clk or posedge rst)
        begin
            if(rst==1)
            begin
                ps<=S1;
                count<=0;
            end
            else

             case (ps)
               S1 : if(count<sec7)
                        begin
                            ps <= S1;
                            count<=count+1;
                        end
                        else
                            begin
                                ps<=S2;
                                count<=0;
                            end
                S2: if (count<sec2) begin
                    ps <= S2;
                    count<=count+1;

                     end
                     else
                     begin
                        ps <= S3;
                        count<=0;
                     end 
                S3: if (count<sec5) begin
                    ps <= S3;
                    count<=count+1;
                    
                end
                else 
                begin
                    ps <= S4;
                    count<=0;
                end   
                S4:  if (count<sec2) begin
                    ps<= S4;
                    count<=count+1;
                    
                end     
                else
                begin
                    ps <=S5;
                    count<=0;
                end  
                S5: if (count<sec3) begin
                    ps<= S5;
                    count<= count+1;
                    
                end   
                else
                begin
                    ps<= S6;
                    count<= 0;

                end
                S6: if (count<sec2) begin
                    ps <=S6;
                    count<= count+1;
                end
                else
                begin
                    ps <= S1;
                    count<=0;
                end

                default: ps <= S1;
             endcase


        end







        always@(ps)
            begin
                case (ps)
                  S1  : 
                  begin
                    light_M1<=3'b001;
                    light_M2<=3'b001;
                    light_MT<=3'b100;
                    light_s<=3'b100;
                
                  end
                  S2:
                  begin
                    light_M1<=3'b001;
                    light_M2<=3'b010;
                    light_MT<=3'b100;
                    light_s<=3'b100;
                  end
                  S3:
                  begin
                    light_M1<=3'b001;
                    light_M2<=3'b100;
                    light_MT<=3'b001;
                    light_s<=3'b100;
                  end
                  S4:
                  begin
                    light_M1<=3'b010;
                    light_M2<=3'b100;
                    light_MT<=3'b010;
                    light_s<=3'b100;
                    
                  end
                  S5:
                  begin
                    light_M1<=3'b100;
                    light_M2<=3'b100;
                    light_MT<=3'b100;
                    light_s<=3'b001;
                  end
                  S6:
                  begin
                    light_M1<=3'b100;
                    light_M2<=3'b100;
                    light_MT<=3'b100;
                    light_s<=3'b010;
                  end
                    default: 
                    begin
                        light_M1<=3'b000;
                        light_M2<=3'b000;
                        light_MT<=3'b000;
                        light_s<=3'b000;
                    end
                endcase

            end



endmodule

light_tb.v
`timescale 1ns/1ps
`include "traffic_controller.v"
module  traffic_light_controller_tb;
reg clk;
reg rst;
reg [3:0]count ;
    reg [2:0] ps ;
wire [2:0]light_M1 ;
wire [2:0]light_s ;
wire [2:0]light_MT ;
wire [2:0]light_M2 ;
traffic_light_controller uut( clk,rst,light_M1,light_s,light_MT,light_M2);
 initial begin
    $dumpfile("light_tb.vcd");
    $dumpvars(0,traffic_light_controller_tb);
     $monitor ($time,"clk=%b,rst=%b,count=%b,ps=%b",clk,rst,count,ps);
   
        
    
     clk=1'b0;
     forever #5 clk =~clk;
   
 end
 initial begin
   
    
   
     rst=0;
        #5 rst=1;
        #5 rst=0;
        #200;
        $finish;
    end

   
 
endmodule

light_tb.vcd
$date
	Sun Jun 30 21:45:33 2024
$end
$version
	Icarus Verilog
$end
$timescale
	1ps
$end
$scope module traffic_light_controller_tb $end
$var wire 3 ! light_s [2:0] $end
$var wire 3 " light_MT [2:0] $end
$var wire 3 # light_M2 [2:0] $end
$var wire 3 $ light_M1 [2:0] $end
$var reg 1 % clk $end
$var reg 4 & count [3:0] $end
$var reg 3 ' ps [2:0] $end
$var reg 1 ( rst $end
$scope module uut $end
$var wire 1 % clk $end
$var wire 1 ( rst $end
$var parameter 32 ) S1 $end
$var parameter 32 * S2 $end
$var parameter 32 + S3 $end
$var parameter 32 , S4 $end
$var parameter 32 - S5 $end
$var parameter 32 . S6 $end
$var parameter 32 / sec2 $end
$var parameter 32 0 sec3 $end
$var parameter 32 1 sec5 $end
$var parameter 32 2 sec7 $end
$var reg 4 3 count [3:0] $end
$var reg 3 4 light_M1 [2:0] $end
$var reg 3 5 light_M2 [2:0] $end
$var reg 3 6 light_MT [2:0] $end
$var reg 3 7 light_s [2:0] $end
$var reg 3 8 ps [2:0] $end
$upscope $end
$upscope $end
$enddefinitions $end
$comment Show the parameter values. $end
$dumpall
b111 2
b101 1
b11 0
b10 /
b101 .
b100 -
b11 ,
b10 +
b1 *
b0 )
$end
#0
$dumpvars
bx 8
bx 7
bx 6
bx 5
bx 4
bx 3
0(
bx '
bx &
0%
bx $
bx #
bx "
bx !
$end
#5000
b100 !
b100 7
b100 "
b100 6
b1 #
b1 5
b1 $
b1 4
b0 3
b0 8
1(
1%
#10000
0(
0%
#15000
b1 3
1%
#20000
0%
#25000
b10 3
1%
#30000
0%
#35000
b11 3
1%
#40000
0%
#45000
b100 3
1%
#50000
0%
#55000
b101 3
1%
#60000
0%
#65000
b110 3
1%
#70000
0%
#75000
b111 3
1%
#80000
0%
#85000
b10 #
b10 5
b0 3
b1 8
1%
#90000
0%
#95000
b1 3
1%
#100000
0%
#105000
b10 3
1%
#110000
0%
#115000
b1 "
b1 6
b100 #
b100 5
b0 3
b10 8
1%
#120000
0%
#125000
b1 3
1%
#130000
0%
#135000
b10 3
1%
#140000
0%
#145000
b11 3
1%
#150000
0%
#155000
b100 3
1%
#160000
0%
#165000
b101 3
1%
#170000
0%
#175000
b10 "
b10 6
b10 $
b10 4
b0 3
b11 8
1%
#180000
0%
#185000
b1 3
1%
#190000
0%
#195000
b10 3
1%
#200000
0%
#205000
b1 !
b1 7
b100 "
b100 6
b100 $
b100 4
b0 3
b100 8
1%
